fortimail/__init__.py
fortimail/client.py
fortimail/exceptions.py
fortimail/utils.py
fortimail-0.1.0.dist-info/METADATA
fortimail-0.1.0.dist-info/WHEEL
fortimail-0.1.0.dist-info/top_level.txt
fortimail-0.1.0.dist-info/RECORD
