Metadata-Version: 2.1
Name: fortimail
Version: 0.1.0
Summary: Fortimail Rest API Client
Home-page: https://github.com/surfer190/fortimail.git
Author: surfer190
Author-email: stephenh@startmail.com
License: UNKNOWN
Platform: UNKNOWN
Classifier: Development Status :: 1 - Planning
Classifier: Operating System :: OS Independent
Classifier: Programming Language :: Python :: 3.6
Classifier: Programming Language :: Python :: 3.7
Classifier: Programming Language :: Python :: 3.8
Classifier: Programming Language :: Python :: 3 :: Only
Classifier: License :: OSI Approved :: GNU General Public License v3 (GPLv3)
Classifier: Natural Language :: English
Requires-Python: >=3.6
Requires-Dist: requests
